main.py
aws_services/__init__.py
aws_services/api_gateway/__init__.py
aws_services/api_gateway/api_gateway_constants.py
aws_services/api_gateway/api_gateway_service.py
aws_services/dat_lambda/__init__.py
aws_services/dat_lambda/lambda_constants.py
aws_services/dat_lambda/lambda_service.py
aws_services/dynamodb/__init__.py
aws_services/dynamodb/dynamodb_constants.py
aws_services/dynamodb/dynamodb_service.py
aws_services/emr/__init__.py
aws_services/emr/emr_constants.py
aws_services/emr/emr_service.py
aws_services/fargate/__init__.py
aws_services/fargate/fargate_constants.py
aws_services/fargate/fargate_service.py
aws_services/glue/__init__.py
aws_services/glue/glue_constants.py
aws_services/glue/glue_service.py
aws_services/kinesis_firehose/__init__.py
aws_services/kinesis_firehose/firehose_constants.py
aws_services/kinesis_firehose/kinesis_firehose_service.py
aws_services/kinesis_stream/__init__.py
aws_services/kinesis_stream/kinesis_stream_constants.py
aws_services/kinesis_stream/kinesis_stream_service.py
aws_services/rds/__init__.py
aws_services/rds/rds_constants.py
aws_services/rds/rds_service.py
aws_services/redshift/__init__.py
aws_services/redshift/redshift_constants.py
aws_services/redshift/redshift_service.py
aws_services/s3/__init__.py
aws_services/s3/s3_constants.py
aws_services/s3/s3_service.py
aws_services/ses/__init__.py
aws_services/ses/ses_constants.py
aws_services/ses/ses_service.py
aws_services/sns/__init__.py
aws_services/sns/sns_constants.py
aws_services/sns/sns_service.py
aws_services/sqs/__init__.py
aws_services/sqs/sqs_constants.py
aws_services/sqs/sqs_service.py
common/__init__.py
common/constants/__init__.py
common/constants/application_constants.py
common/service/__init__.py
common/service/dat_service.py
common/templates/audit_report.html
common/templates/index.html
common/utils/__init__.py
common/utils/helper.py
common/utils/initialize_logger.py
common/utils/instance_initializer.py
cloud2-0.2.1.dist-info/METADATA
cloud2-0.2.1.dist-info/WHEEL
cloud2-0.2.1.dist-info/entry_points.txt
cloud2-0.2.1.dist-info/top_level.txt
cloud2-0.2.1.dist-info/RECORD
